parangonar/__init__.py
parangonar/assets/alignment_transformer_checkpoint.pt
parangonar/assets/mozart_k265_var1.match
parangonar/assets/thegluenote_small_checkpoint.pt
parangonar/dp/__init__.py
parangonar/dp/dtw.py
parangonar/dp/metrics.py
parangonar/dp/nwtw.py
parangonar/dp/oltw.py
parangonar/dp/t_oltw.py
parangonar/evaluate/__init__.py
parangonar/evaluate/eval.py
parangonar/evaluate/io.py
parangonar/evaluate/plot.py
parangonar/evaluate/simple.py
parangonar/match/__init__.py
parangonar/match/gluenote_utils.py
parangonar/match/matchers.py
parangonar/match/online_matchers.py
parangonar/match/preprocessors.py
parangonar/match/pretrained_models.py
parangonar/match/utils.py
parangonar/mismatch/__init__.py
parangonar/mismatch/repeat_identification.py
parangonar/mismatch/subpart.py
parangonar-3.2.0.dist-info/licenses/LICENSE
parangonar-3.2.0.dist-info/METADATA
parangonar-3.2.0.dist-info/WHEEL
parangonar-3.2.0.dist-info/top_level.txt
parangonar-3.2.0.dist-info/RECORD
