Metadata-Version: 2.4
Name: parangonar
Version: 3.2.0
Summary: Music Alignment
Author: Silvan Peter
License: Apache-2.0
Project-URL: Homepage, https://github.com/sildater/parangonar
Keywords: match,alignment,midi,performance,score
Classifier: Programming Language :: Python
Classifier: Programming Language :: Python :: 3
Requires-Python: >=3.7
License-File: LICENSE
Requires-Dist: numpy
Requires-Dist: scipy
Requires-Dist: torch
Requires-Dist: matplotlib
Requires-Dist: partitura>=1.6.0
Requires-Dist: symusic
Requires-Dist: miditok
Requires-Dist: numba
Dynamic: license-file
